{
  "type": "FeatureCollection",
  "features": [
    {
      "type": "Feature",
      "id": "ZNTRANGE.fid--66ea06ce_18d67a1c1b2_57b0",
      "geometry": {
        "type": "Polygon",
        "coordinates": [
          [
            [
              106.80476614,
              -6.26530519
            ],
            [
              106.80460878,
              -6.26528958
            ],
            [
              106.80460818,
              -6.26504239
            ],
            [
              106.80460768,
              -6.26486494
            ],
            [
              106.80460594,
              -6.26480483
            ],
            [
              106.80462744,
              -6.26480363
            ],
            [
              106.8046244,
              -6.26475231
            ],
            [
              106.8046234,
              -6.26473532
            ],
            [
              106.80459618,
              -6.26473453
            ],
            [
              106.80459685,
              -6.26461058
            ],
            [
              106.80459433,
              -6.26446829
            ],
            [
              106.80459104,
              -6.26423428
            ],
            [
              106.80458803,
              -6.26401956
            ],
            [
              106.80448189,
              -6.26404062
            ],
            [
              106.80448222,
              -6.26406466
            ],
            [
              106.80443528,
              -6.26407206
            ],
            [
              106.8044375,
              -6.263997
            ],
            [
              106.80441133,
              -6.26399115
            ],
            [
              106.80439907,
              -6.26383177
            ],
            [
              106.80456323,
              -6.26380145
            ],
            [
              106.80466178,
              -6.2637949
            ],
            [
              106.80468516,
              -6.26378634
            ],
            [
              106.80467744,
              -6.26375136
            ],
            [
              106.80467095,
              -6.2635201
            ],
            [
              106.80459052,
              -6.26352655
            ],
            [
              106.80459053,
              -6.26354911
            ],
            [
              106.80450806,
              -6.26355213
            ],
            [
              106.80449782,
              -6.26344271
            ],
            [
              106.80456614,
              -6.26343798
            ],
            [
              106.80455375,
              -6.26322133
            ],
            [
              106.80456368,
              -6.26317156
            ],
            [
              106.80446937,
              -6.26316539
            ],
            [
              106.80447649,
              -6.26276123
            ],
            [
              106.80446683,
              -6.26254158
            ],
            [
              106.80446673,
              -6.26237409
            ],
            [
              106.80445467,
              -6.26219464
            ],
            [
              106.80445589,
              -6.26213429
            ],
            [
              106.80437403,
              -6.26212488
            ],
            [
              106.80429924,
              -6.26211691
            ],
            [
              106.80427133,
              -6.26211385
            ],
            [
              106.8042794,
              -6.2620254
            ],
            [
              106.80428516,
              -6.26196221
            ],
            [
              106.80429629,
              -6.26189203
            ],
            [
              106.80433459,
              -6.26189375
            ],
            [
              106.80434042,
              -6.26183101
            ],
            [
              106.8043453,
              -6.26172532
            ],
            [
              106.80435735,
              -6.26166414
            ],
            [
              106.80438502,
              -6.26156319
            ],
            [
              106.80438897,
              -6.26154725
            ],
            [
              106.80436931,
              -6.26154184
            ],
            [
              106.80425952,
              -6.2615188
            ],
            [
              106.80421308,
              -6.2615207
            ],
            [
              106.80413146,
              -6.26149246
            ],
            [
              106.80403525,
              -6.26145916
            ],
            [
              106.80399452,
              -6.26144507
            ],
            [
              106.80400035,
              -6.26141769
            ],
            [
              106.80373664,
              -6.26137906
            ],
            [
              106.80369529,
              -6.2613699
            ],
            [
              106.80372426,
              -6.26121855
            ],
            [
              106.80371423,
              -6.26118862
            ],
            [
              106.80352528,
              -6.26116022
            ],
            [
              106.80349948,
              -6.26115085
            ],
            [
              106.80349293,
              -6.2611952
            ],
            [
              106.8032358,
              -6.26114905
            ],
            [
              106.80323007,
              -6.26120625
            ],
            [
              106.80319171,
              -6.261178
            ],
            [
              106.8030155,
              -6.26112072
            ],
            [
              106.80300532,
              -6.26111741
            ],
            [
              106.80296512,
              -6.26129139
            ],
            [
              106.80290432,
              -6.26127372
            ],
            [
              106.80273077,
              -6.26121572
            ],
            [
              106.80260093,
              -6.26117233
            ],
            [
              106.80256682,
              -6.26115391
            ],
            [
              106.80257932,
              -6.26113527
            ],
            [
              106.80263513,
              -6.26100221
            ],
            [
              106.80242876,
              -6.26088809
            ],
            [
              106.80234542,
              -6.26095859
            ],
            [
              106.80222214,
              -6.26126235
            ],
            [
              106.80214214,
              -6.26140991
            ],
            [
              106.8020287,
              -6.26137933
            ],
            [
              106.80200938,
              -6.26142507
            ],
            [
              106.80200357,
              -6.26146216
            ],
            [
              106.80172964,
              -6.26141631
            ],
            [
              106.80158456,
              -6.26139203
            ],
            [
              106.80141338,
              -6.26136338
            ],
            [
              106.80133292,
              -6.2616552
            ],
            [
              106.80130869,
              -6.26176957
            ],
            [
              106.80118499,
              -6.26174201
            ],
            [
              106.80116246,
              -6.26184187
            ],
            [
              106.80112879,
              -6.26183119
            ],
            [
              106.80106642,
              -6.26182158
            ],
            [
              106.80101062,
              -6.26181562
            ],
            [
              106.8010112,
              -6.26179796
            ],
            [
              106.80094414,
              -6.26179121
            ],
            [
              106.80093406,
              -6.26186895
            ],
            [
              106.80086861,
              -6.26185924
            ],
            [
              106.80086976,
              -6.26180564
            ],
            [
              106.80083666,
              -6.26179722
            ],
            [
              106.80082428,
              -6.26188766
            ],
            [
              106.80060811,
              -6.2618605
            ],
            [
              106.80055955,
              -6.26184968
            ],
            [
              106.80056119,
              -6.26183999
            ],
            [
              106.80039484,
              -6.26183009
            ],
            [
              106.8003912,
              -6.26184764
            ],
            [
              106.80036952,
              -6.26184707
            ],
            [
              106.80036398,
              -6.26184682
            ],
            [
              106.80035753,
              -6.26204828
            ],
            [
              106.80035932,
              -6.2620572
            ],
            [
              106.80035763,
              -6.26209018
            ],
            [
              106.80033816,
              -6.26209407
            ],
            [
              106.80004662,
              -6.26211377
            ],
            [
              106.80004287,
              -6.26207809
            ],
            [
              106.80003896,
              -6.26190508
            ],
            [
              106.80002992,
              -6.26150577
            ],
            [
              106.79996129,
              -6.26150473
            ],
            [
              106.79989234,
              -6.26150369
            ],
            [
              106.79989217,
              -6.26146529
            ],
            [
              106.79989134,
              -6.2613654
            ],
            [
              106.79988204,
              -6.26136559
            ],
            [
              106.79988317,
              -6.26129053
            ],
            [
              106.79996595,
              -6.26128713
            ],
            [
              106.7999763,
              -6.26114903
            ],
            [
              106.79997234,
              -6.26111909
            ],
            [
              106.79998897,
              -6.26111998
            ],
            [
              106.79998391,
              -6.26093583
            ],
            [
              106.79998966,
              -6.26078861
            ],
            [
              106.79991022,
              -6.2607979
            ],
            [
              106.79991369,
              -6.26065569
            ],
            [
              106.79992837,
              -6.26065551
            ],
            [
              106.79992861,
              -6.2605462
            ],
            [
              106.79992707,
              -6.26054625
            ],
            [
              106.79992996,
              -6.26049651
            ],
            [
              106.79994133,
              -6.26030061
            ],
            [
              106.7999387,
              -6.2602131
            ],
            [
              106.79971164,
              -6.26022422
            ],
            [
              106.79966129,
              -6.26022057
            ],
            [
              106.79966503,
              -6.26028236
            ],
            [
              106.79963467,
              -6.260284
            ],
            [
              106.79948216,
              -6.26029218
            ],
            [
              106.79948079,
              -6.26030582
            ],
            [
              106.79948613,
              -6.26041424
            ],
            [
              106.79945955,
              -6.26041493
            ],
            [
              106.79942183,
              -6.26041654
            ],
            [
              106.79934716,
              -6.26041977
            ],
            [
              106.79935106,
              -6.26054434
            ],
            [
              106.79936007,
              -6.26054385
            ],
            [
              106.7993666,
              -6.26082736
            ],
            [
              106.79939169,
              -6.26082697
            ],
            [
              106.79939429,
              -6.26090149
            ],
            [
              106.79939737,
              -6.26108642
            ],
            [
              106.79944166,
              -6.26107618
            ],
            [
              106.79944746,
              -6.26144414
            ],
            [
              106.79949524,
              -6.26144432
            ],
            [
              106.79951848,
              -6.26149588
            ],
            [
              106.79953615,
              -6.26213048
            ],
            [
              106.79953797,
              -6.26222774
            ],
            [
              106.79934045,
              -6.26223315
            ],
            [
              106.79908493,
              -6.26223589
            ],
            [
              106.79908466,
              -6.2622178
            ],
            [
              106.79890875,
              -6.26222832
            ],
            [
              106.79884721,
              -6.26223078
            ],
            [
              106.7987232,
              -6.26223349
            ],
            [
              106.79866944,
              -6.26223348
            ],
            [
              106.79866947,
              -6.26226803
            ],
            [
              106.79859017,
              -6.26225889
            ],
            [
              106.79860099,
              -6.26218286
            ],
            [
              106.79853972,
              -6.26217566
            ],
            [
              106.79852725,
              -6.26226172
            ],
            [
              106.79841981,
              -6.26224836
            ],
            [
              106.79842788,
              -6.26215949
            ],
            [
              106.7984432,
              -6.2621599
            ],
            [
              106.79844468,
              -6.26214973
            ],
            [
              106.79846304,
              -6.26215114
            ],
            [
              106.79846617,
              -6.26210914
            ],
            [
              106.79824974,
              -6.26208915
            ],
            [
              106.79820315,
              -6.26208485
            ],
            [
              106.79820066,
              -6.26208463
            ],
            [
              106.79819698,
              -6.26211507
            ],
            [
              106.79815571,
              -6.26211024
            ],
            [
              106.79815211,
              -6.26214019
            ],
            [
              106.79807384,
              -6.26212957
            ],
            [
              106.7980835,
              -6.26204154
            ],
            [
              106.79805514,
              -6.26203774
            ],
            [
              106.79805302,
              -6.26206112
            ],
            [
              106.79792736,
              -6.26204182
            ],
            [
              106.79793007,
              -6.26200861
            ],
            [
              106.79786923,
              -6.26200143
            ],
            [
              106.79782273,
              -6.26199056
            ],
            [
              106.7977813,
              -6.26199801
            ],
            [
              106.79762985,
              -6.26197471
            ],
            [
              106.79762917,
              -6.26197804
            ],
            [
              106.79762323,
              -6.26197676
            ],
            [
              106.79762072,
              -6.26199111
            ],
            [
              106.79756933,
              -6.26198348
            ],
            [
              106.79756094,
              -6.26195585
            ],
            [
              106.79759035,
              -6.26181087
            ],
            [
              106.79757673,
              -6.26180813
            ],
            [
              106.79751201,
              -6.26179472
            ],
            [
              106.79749602,
              -6.26179144
            ],
            [
              106.79753851,
              -6.26163842
            ],
            [
              106.79740499,
              -6.26159471
            ],
            [
              106.79742099,
              -6.26156427
            ],
            [
              106.79727855,
              -6.26152652
            ],
            [
              106.79726586,
              -6.2614963
            ],
            [
              106.79723352,
              -6.26154669
            ],
            [
              106.79720637,
              -6.26163389
            ],
            [
              106.79717744,
              -6.26172941
            ],
            [
              106.79708253,
              -6.26214346
            ],
            [
              106.79723155,
              -6.26214519
            ],
            [
              106.79722083,
              -6.26219907
            ],
            [
              106.79718684,
              -6.26263579
            ],
            [
              106.79777879,
              -6.2626354
            ],
            [
              106.79791223,
              -6.26264219
            ],
            [
              106.79808264,
              -6.26265641
            ],
            [
              106.79808147,
              -6.26267639
            ],
            [
              106.7981116,
              -6.26267714
            ],
            [
              106.79811138,
              -6.26268659
            ],
            [
              106.79814637,
              -6.26267684
            ],
            [
              106.79837059,
              -6.26268064
            ],
            [
              106.79850916,
              -6.2626894
            ],
            [
              106.79876419,
              -6.26269806
            ],
            [
              106.799109,
              -6.26271021
            ],
            [
              106.79920747,
              -6.26270073
            ],
            [
              106.79948892,
              -6.26269993
            ],
            [
              106.7998047,
              -6.26271845
            ],
            [
              106.79986574,
              -6.26272066
            ],
            [
              106.79986705,
              -6.26283689
            ],
            [
              106.80001001,
              -6.26284019
            ],
            [
              106.8000048,
              -6.26265608
            ],
            [
              106.80010292,
              -6.26265772
            ],
            [
              106.80029175,
              -6.262667
            ],
            [
              106.80045143,
              -6.2626823
            ],
            [
              106.80051656,
              -6.26266977
            ],
            [
              106.80061406,
              -6.26267443
            ],
            [
              106.80061587,
              -6.26265399
            ],
            [
              106.80059514,
              -6.26265242
            ],
            [
              106.8006025,
              -6.2625963
            ],
            [
              106.80060701,
              -6.26259662
            ],
            [
              106.80061961,
              -6.26253736
            ],
            [
              106.80061644,
              -6.26252841
            ],
            [
              106.80064185,
              -6.2623793
            ],
            [
              106.80075769,
              -6.26239604
            ],
            [
              106.80077779,
              -6.26224026
            ],
            [
              106.80077832,
              -6.26221966
            ],
            [
              106.80080828,
              -6.26221961
            ],
            [
              106.80081059,
              -6.26221058
            ],
            [
              106.80082603,
              -6.26213989
            ],
            [
              106.80093878,
              -6.26214141
            ],
            [
              106.80093964,
              -6.26222371
            ],
            [
              106.80102661,
              -6.26221285
            ],
            [
              106.80102821,
              -6.26223207
            ],
            [
              106.80117303,
              -6.26221552
            ],
            [
              106.80116338,
              -6.26209041
            ],
            [
              106.8011795,
              -6.26208012
            ],
            [
              106.80128159,
              -6.2620826
            ],
            [
              106.80139587,
              -6.26208692
            ],
            [
              106.80140038,
              -6.2620871
            ],
            [
              106.80140134,
              -6.26204952
            ],
            [
              106.80147801,
              -6.26204755
            ],
            [
              106.80153212,
              -6.26204517
            ],
            [
              106.80154115,
              -6.2620449
            ],
            [
              106.80154096,
              -6.26205394
            ],
            [
              106.80154774,
              -6.26205373
            ],
            [
              106.80154757,
              -6.26206187
            ],
            [
              106.80158334,
              -6.26205906
            ],
            [
              106.80159485,
              -6.26205814
            ],
            [
              106.80159458,
              -6.26207822
            ],
            [
              106.80159428,
              -6.2621
            ],
            [
              106.80159322,
              -6.26212047
            ],
            [
              106.80164623,
              -6.2621201
            ],
            [
              106.80164642,
              -6.26211167
            ],
            [
              106.80168691,
              -6.26211258
            ],
            [
              106.80176167,
              -6.26211017
            ],
            [
              106.80176189,
              -6.26207474
            ],
            [
              106.80177683,
              -6.26207463
            ],
            [
              106.80182834,
              -6.26207416
            ],
            [
              106.80182603,
              -6.26210564
            ],
            [
              106.80182642,
              -6.26211241
            ],
            [
              106.80185041,
              -6.26211354
            ],
            [
              106.80186579,
              -6.26211427
            ],
            [
              106.80197265,
              -6.26211962
            ],
            [
              106.80197611,
              -6.26209043
            ],
            [
              106.80206368,
              -6.26207787
            ],
            [
              106.80204259,
              -6.2619335
            ],
            [
              106.80212072,
              -6.26192651
            ],
            [
              106.80212226,
              -6.26192637
            ],
            [
              106.80211813,
              -6.26190931
            ],
            [
              106.80213173,
              -6.26188236
            ],
            [
              106.8021513,
              -6.26181931
            ],
            [
              106.80214628,
              -6.26176892
            ],
            [
              106.80223132,
              -6.26176697
            ],
            [
              106.80223648,
              -6.26174161
            ],
            [
              106.80223437,
              -6.26166039
            ],
            [
              106.80223323,
              -6.2616466
            ],
            [
              106.8023711,
              -6.26164436
            ],
            [
              106.8023712,
              -6.26164846
            ],
            [
              106.80237259,
              -6.26170184
            ],
            [
              106.8023739,
              -6.26175213
            ],
            [
              106.80248416,
              -6.26173181
            ],
            [
              106.80248678,
              -6.26182112
            ],
            [
              106.80246579,
              -6.26190993
            ],
            [
              106.80251217,
              -6.26191262
            ],
            [
              106.80267065,
              -6.2619218
            ],
            [
              106.80288001,
              -6.26192141
            ],
            [
              106.80292609,
              -6.26192263
            ],
            [
              106.80317363,
              -6.26192919
            ],
            [
              106.80321603,
              -6.2619299
            ],
            [
              106.80320123,
              -6.26211761
            ],
            [
              106.80326989,
              -6.26222075
            ],
            [
              106.80329598,
              -6.26222451
            ],
            [
              106.80343754,
              -6.26223172
            ],
            [
              106.80348772,
              -6.26223486
            ],
            [
              106.80354272,
              -6.26224975
            ],
            [
              106.80355274,
              -6.26226583
            ],
            [
              106.803572,
              -6.2622683
            ],
            [
              106.80358389,
              -6.26227693
            ],
            [
              106.80362155,
              -6.26227841
            ],
            [
              106.80363072,
              -6.26228128
            ],
            [
              106.80368585,
              -6.26228564
            ],
            [
              106.8037615,
              -6.26229162
            ],
            [
              106.80380015,
              -6.26229468
            ],
            [
              106.80381497,
              -6.26229615
            ],
            [
              106.8038167,
              -6.26229879
            ],
            [
              106.80382687,
              -6.26231923
            ],
            [
              106.80383633,
              -6.26238895
            ],
            [
              106.80384423,
              -6.26246073
            ],
            [
              106.8038894,
              -6.26246284
            ],
            [
              106.80392213,
              -6.26247035
            ],
            [
              106.80391272,
              -6.26264599
            ],
            [
              106.80378011,
              -6.26264252
            ],
            [
              106.80378108,
              -6.2627236
            ],
            [
              106.80377876,
              -6.26276032
            ],
            [
              106.80363459,
              -6.26275322
            ],
            [
              106.80361937,
              -6.26306307
            ],
            [
              106.80361815,
              -6.26310934
            ],
            [
              106.80360827,
              -6.26316394
            ],
            [
              106.80372064,
              -6.26319795
            ],
            [
              106.80371836,
              -6.26320546
            ],
            [
              106.8037565,
              -6.26321435
            ],
            [
              106.8037906,
              -6.26321848
            ],
            [
              106.80392361,
              -6.26324574
            ],
            [
              106.8038833,
              -6.26339596
            ],
            [
              106.80387967,
              -6.26340982
            ],
            [
              106.80383558,
              -6.26339902
            ],
            [
              106.80380766,
              -6.26353764
            ],
            [
              106.80381407,
              -6.2635381
            ],
            [
              106.80390057,
              -6.26354433
            ],
            [
              106.80390454,
              -6.26354522
            ],
            [
              106.8039038,
              -6.26363533
            ],
            [
              106.80391196,
              -6.26363493
            ],
            [
              106.803909,
              -6.26365038
            ],
            [
              106.80391131,
              -6.26367513
            ],
            [
              106.80392232,
              -6.26378029
            ],
            [
              106.80390373,
              -6.26391497
            ],
            [
              106.80389141,
              -6.26406929
            ],
            [
              106.80388523,
              -6.26412468
            ],
            [
              106.80387564,
              -6.26432507
            ],
            [
              106.80387134,
              -6.26450011
            ],
            [
              106.80394669,
              -6.26450148
            ],
            [
              106.80394243,
              -6.26455805
            ],
            [
              106.80397507,
              -6.26455806
            ],
            [
              106.80403113,
              -6.26455753
            ],
            [
              106.80402371,
              -6.26465215
            ],
            [
              106.80401901,
              -6.26465221
            ],
            [
              106.80401732,
              -6.26468563
            ],
            [
              106.80401335,
              -6.2647642
            ],
            [
              106.80401581,
              -6.26490771
            ],
            [
              106.80405314,
              -6.26490615
            ],
            [
              106.80405693,
              -6.26501683
            ],
            [
              106.8040785,
              -6.26501614
            ],
            [
              106.80407511,
              -6.26507665
            ],
            [
              106.80407112,
              -6.26514783
            ],
            [
              106.80404668,
              -6.26514959
            ],
            [
              106.80404613,
              -6.26518684
            ],
            [
              106.80398561,
              -6.26518746
            ],
            [
              106.80398623,
              -6.26519501
            ],
            [
              106.80398599,
              -6.26525989
            ],
            [
              106.80398583,
              -6.26530359
            ],
            [
              106.80404354,
              -6.2653017
            ],
            [
              106.80404917,
              -6.26545128
            ],
            [
              106.80406343,
              -6.26545092
            ],
            [
              106.80415482,
              -6.26544862
            ],
            [
              106.8041563,
              -6.26561891
            ],
            [
              106.80400343,
              -6.26562225
            ],
            [
              106.80400363,
              -6.26567913
            ],
            [
              106.80401132,
              -6.26587253
            ],
            [
              106.80403246,
              -6.26587187
            ],
            [
              106.80403757,
              -6.26595645
            ],
            [
              106.80413584,
              -6.26595526
            ],
            [
              106.80417342,
              -6.26600825
            ],
            [
              106.80411425,
              -6.26601438
            ],
            [
              106.8041441,
              -6.26622166
            ],
            [
              106.80434839,
              -6.26621229
            ],
            [
              106.80443375,
              -6.26620651
            ],
            [
              106.80438498,
              -6.26597352
            ],
            [
              106.80476281,
              -6.26595605
            ],
            [
              106.80476007,
              -6.26589002
            ],
            [
              106.8047522,
              -6.26570047
            ],
            [
              106.8047478,
              -6.26555057
            ],
            [
              106.80476525,
              -6.26531714
            ],
            [
              106.80476614,
              -6.26530519
            ]
          ]
        ]
      },
      "geometry_name": "BATAS",
      "properties": {
        "ZONANILAITANAHID": "0DA4F790E808D4AAE063B516140A2223",
        "KANTORID": "7d718fb285f74ab8bf45f8b81b1390ff",
        "NAMAKANTOR": "Kota Jaksel",
        "NOMORZONE": "1098",
        "TAHUNDIBUAT": 2023,
        "RANGENILAI": "> 20.000.000",
        "KELASNILAI": 9
      }
    }
  ],
  "totalFeatures": "unknown",
  "numberReturned": 1,
  "timeStamp": "2024-02-02T02:27:47.202Z",
  "crs": {
    "type": "name",
    "properties": {
      "name": "urn:ogc:def:crs:EPSG::4326"
    }
  }
}